{
  "products": {
    "ASSORTIMENT DE MINI FINANCIERS": {
      "Tittle": "ASSORTIMENT DE MINI FINANCIERS",
      "Description": "48 pièces ASSORTIMENT DE FINANCIERS : • Moelleux aux amandes • Moelleux à la pistache et abricot • Moelleux à la noix de coco • Moelleux aux amandes et griotte • Moelleux aux amandes/noisettes et compotée de pomme • Moelleux chocolat aux pépites de chocol",
      "Icon": "",
      "PreviewImg": "normal-eaf206ea839228a57aec4426e604f8104b0c011c.jpg",
      "BigImg": "big-eaf206ea839228a57aec4426e604f8104b0c011c.jpg",
      "ProductUrl": "mini-financiers",
      "Allergens": [
        "Gluten",
        "Oeufs",
        "Soja",
        "Fruits à coques",
        "Lait"
      ]
    },
    "NAPPAGE POUR 10 PERSONNES": {
      "Tittle": "NAPPAGE POUR 10 PERSONNES",
      "Description": "Nappage couleur chocolat et chemin de table vert anis. Votre cocktail sera nappé et dressé.",
      "Icon": "",
      "PreviewImg": "normal-9fe562782e2bb5123ba4c790daec13ca3621b7ca.jpg",
      "BigImg": "big-9fe562782e2bb5123ba4c790daec13ca3621b7ca.jpg",
      "ProductUrl": "nappage",
      "Allergens": []
    },
    "PLATEAU SUCRE OUESSANT": {
      "Tittle": "PLATEAU SUCRE OUESSANT",
      "Description": "40 pièces Mini canelés de Bordeaux, macarons A déguster dans les 2h après la livraison.",
      "Icon": "",
      "PreviewImg": "normal-a1fdf0ab30d8cf0ec86eddf0ca6d544e98d100ea.jpg",
      "BigImg": "big-a1fdf0ab30d8cf0ec86eddf0ca6d544e98d100ea.jpg",
      "ProductUrl": "ouessant",
      "Allergens": [
        "Gluten",
        "Oeufs",
        "Soja",
        "Fruits à coques",
        "Lait"
      ]
    },
    "ASSORTIMENT COLOR POWER": {
      "Tittle": "ASSORTIMENT COLOR POWER",
      "Description": "40 pièces • Verrines yaourt grec et brunoise de fruits • Macaron",
      "Icon": "",
      "PreviewImg": "normal-466bd66e0c09bda3941e42642893d60af7aaa1b5.jpg",
      "BigImg": "big-466bd66e0c09bda3941e42642893d60af7aaa1b5.jpg",
      "ProductUrl": "color-power",
      "Allergens": [
        "Lait",
        "Gluten",
        "Oeufs",
        "Soja",
        "Fruits à coques"
      ]
    },
    "PETITS FOURS PRESTIGE": {
      "Tittle": "PETITS FOURS PRESTIGE",
      "Description": "48 pièces ASSORTIMENT DE : • Lingots marron cassis • Mini tiramisu fraise framboise • Pannacotta coco, mangue et passion • Mini choux praliné • Carrés 3 chocolats • Mini cheesecake caramel • Financier abricot vanille • Financier fruits rouges & amandes",
      "Icon": "",
      "PreviewImg": "normal-580e776a8602a4f5f756b69ebde368056bb8d255.jpg",
      "BigImg": "big-580e776a8602a4f5f756b69ebde368056bb8d255.jpg",
      "ProductUrl": "petits-fours-prestige",
      "Allergens": [
        "Gluten",
        "Oeufs",
        "Poissons",
        "Soja",
        "Fruits à coques",
        "Lait"
      ]
    },
    "ASSORTIMENT TOUR DE FRANCE": {
      "Tittle": "ASSORTIMENT TOUR DE FRANCE",
      "Description": "53 pièces • Canelés de Bordeaux • Meringues • Riz au lait • Verrines fromage blanc fruits rouges",
      "Icon": "",
      "PreviewImg": "normal-c72e496eaca6fab179f96e08c8009cab73a8d9b4.jpg",
      "BigImg": "big-c72e496eaca6fab179f96e08c8009cab73a8d9b4.jpg",
      "ProductUrl": "tour-de-france",
      "Allergens": [
        "Lait",
        "Soja",
        "Sésame",
        "Oeufs",
        "Gluten"
      ]
    },
    "ASSORTIMENT GOURMAND": {
      "Tittle": "ASSORTIMENT GOURMAND",
      "Description": "39 pièces • Verrines lactées fruits • Brownies • Verrines lactées citron & fraise • Verrines lactées purée de pomme & fruits rouges",
      "Icon": "",
      "PreviewImg": "normal-e21cb7176b886db816f87a392b869efb77648073.jpg",
      "BigImg": "big-e21cb7176b886db816f87a392b869efb77648073.jpg",
      "ProductUrl": "assortiment-gourmand",
      "Allergens": [
        "Lait",
        "Oeufs",
        "Gluten",
        "Soja",
        "Fruits à coques"
      ]
    },
    "PLATEAU SUCRE BATZ": {
      "Tittle": "PLATEAU SUCRE BATZ",
      "Description": "40 pièces Verrines aux fruits et yaourt grec, macarons A consommer dans les 2 heures après la livraison",
      "Icon": "",
      "PreviewImg": "normal-1113791c4699c26595e96f346c72f7d2754fac58.jpg",
      "BigImg": "big-1113791c4699c26595e96f346c72f7d2754fac58.jpg",
      "ProductUrl": "batz",
      "Allergens": [
        "Lait",
        "Gluten",
        "Oeufs",
        "Soja",
        "Fruits à coques"
      ]
    },
    "PLATEAU SUCRE CALLOT": {
      "Tittle": "PLATEAU SUCRE CALLOT",
      "Description": "40 pièces  Verrines aux fruits et yaourt grec, verrine au risotto sucré et caramel, verrine yaourt grec brownie et caramel de lait, verrine fruits rouges balsamique A consommer dans les 2 heures après la livraison",
      "Icon": "",
      "PreviewImg": "normal-7f5e4960ba2e5f2fabcc30468e77b5b9d7c58aad.jpg",
      "BigImg": "big-7f5e4960ba2e5f2fabcc30468e77b5b9d7c58aad.jpg",
      "ProductUrl": "callot",
      "Allergens": [
        "Lait",
        "Oeufs",
        "Gluten",
        "Soja",
        "Fruits à coques"
      ]
    },
    "MINI PATISSERIES": {
      "Tittle": "MINI PATISSERIES",
      "Description": "48 pièces ASSORTIMENT DE PÂTISSERIES : • Fars aux pruneaux • Lingots citron • Almondines, crème pâtissière, ananas, pistaches • Carrés framboise vanille • Gâteaux d’antan, ganache chocolat, noisettes hachées • Choux pralinés • Éclairs chocolat, glaçage chocolat • Almondines pistache, crème framboise, framboise",
      "Icon": "",
      "PreviewImg": "normal-4798d18aeda18750c227b9edce22004452c76997.jpg",
      "BigImg": "big-4798d18aeda18750c227b9edce22004452c76997.jpg",
      "ProductUrl": "mini-patisseries",
      "Allergens": [
        "Gluten",
        "Oeufs",
        "Poissons",
        "Soja",
        "Fruits à coques",
        "Lait"
      ]
    },
    "PLATEAU SUCRE OLERON": {
      "Tittle": "PLATEAU SUCRE OLERON",
      "Description": "40 pièces  Mini crèpe au nutella, mini crèpe au caramel, mini canelé de Bordeaux, mini moelleux au chocolat A consommer dans les 2 heures après la livraison",
      "Icon": "",
      "PreviewImg": "normal-32825a3a6c67af17b5c42e5d7698582a95aa3d1a.jpg",
      "BigImg": "big-32825a3a6c67af17b5c42e5d7698582a95aa3d1a.jpg",
      "ProductUrl": "oleron",
      "Allergens": [
        "Lait",
        "Fruits à coques",
        "Gluten",
        "Oeufs",
        "Soja"
      ]
    },
    "PETITES VERRINES": {
      "Tittle": "PETITES VERRINES",
      "Description": "36 pièces ASSORTIMENT DE VERRINES : • Chocolat • Citron meringué • Tiramisu • Vanille/framboise",
      "Icon": "",
      "PreviewImg": "normal-b31906846ec3946b1b159ef66acfb21879a16a0e.jpg",
      "BigImg": "big-b31906846ec3946b1b159ef66acfb21879a16a0e.jpg",
      "ProductUrl": "petites-verrines",
      "Allergens": [
        "Gluten",
        "Oeufs",
        "Poissons",
        "Soja",
        "Fruits à coques",
        "Lait"
      ]
    },
    "MINI TARTES SUCREES": {
      "Tittle": "MINI TARTES SUCREES",
      "Description": "50 pièces ASSORTIMENT DE TARTES : • Crumble rhubarbe • Coulis de fruits rouges • Fondant chocolat caramel • Compotée abricot romarin • Framboise amande",
      "Icon": "",
      "PreviewImg": "normal-3e38585fed8eaf2b56bbc3bcb010a91d8e59f25a.jpg",
      "BigImg": "big-3e38585fed8eaf2b56bbc3bcb010a91d8e59f25a.jpg",
      "ProductUrl": "mini-tartes-sucrees",
      "Allergens": [
        "Gluten",
        "Oeufs",
        "Soja",
        "Fruits à coques",
        "Lait"
      ]
    },
    "PLATEAU SUCRE MOLENE": {
      "Tittle": "PLATEAU SUCRE MOLENE",
      "Description": "40 pièces Mini muffin fruits rouges, mini muffin caramel amandes, mini muffin nutella, mini muffin chocolat",
      "Icon": "",
      "PreviewImg": "normal-897c3cf0b567e6608b8d55fb4ab22412f40796b8.jpg",
      "BigImg": "big-897c3cf0b567e6608b8d55fb4ab22412f40796b8.jpg",
      "ProductUrl": "molene",
      "Allergens": [
        "Lait",
        "Fruits à coques",
        "Gluten",
        "Oeufs",
        "Soja"
      ]
    },
    "AGANTON": {
      "Tittle": "AGANTON",
      "Description": "41 pièces Assortiment de : Canelés de Bordeaux  Brownies Verrines riz au lait et noisettes  Verrine yaourt grec à la vanille et brunoise de fruits",
      "Icon": "",
      "PreviewImg": "normal-a429c49c0887715d6ea79e0240c224920405bb1c.jpg",
      "BigImg": "big-a429c49c0887715d6ea79e0240c224920405bb1c.jpg",
      "ProductUrl": "aganton",
      "Allergens": [
        "Lait",
        "Fruits à coques",
        "Gluten",
        "Oeufs",
        "Soja"
      ]
    },
    "PLATEAU SUCRE GLENAN": {
      "Tittle": "PLATEAU SUCRE GLENAN",
      "Description": "40 pièces Verrine au risotto sucré et caramel, mini canelés de Bordeaux A consommer dans les 2 heures après la livraison",
      "Icon": "",
      "PreviewImg": "normal-fd1d65b4b3658f4503c40dea9f20168be7dca4aa.jpg",
      "BigImg": "big-fd1d65b4b3658f4503c40dea9f20168be7dca4aa.jpg",
      "ProductUrl": "glenan",
      "Allergens": [
        "Lait",
        "Gluten",
        "Oeufs",
        "Soja"
      ]
    },
    "MACARONS": {
      "Tittle": "MACARONS",
      "Description": "36 pièces Assortiment de macarons : Vanille Pistache Café Framboise Chocolat Citron",
      "Icon": "",
      "PreviewImg": "normal-39b96113ebb03ddb529d11fdef8108ab8761f311.jpg",
      "BigImg": "big-39b96113ebb03ddb529d11fdef8108ab8761f311.jpg",
      "ProductUrl": "macarons-par-36p",
      "Allergens": [
        "Gluten",
        "Oeufs",
        "Soja",
        "Fruits à coques",
        "Lait"
      ]
    }
  },
  "head": {
    "Header": "QUELLE DOUCEUR SOUHAITEZ-VOUS ?",
    "FiltersCat": [
      "Grandes Salades et Plateaux",
      "Plateaux de fromages, desserts",
      "Cocktail salé",
      "Cocktail sucré",
      "Plateaux à partager"
    ],
    "FiltersSpe": []
  }
}